{"1":{"name":"Lauren","message":"Message from my buddy"},"2":{"name":"Lauren","message":"Can you hear me?"},"3":{"name":"Lauren","message":"Hey"},"4":{"name":"Jason","message":"How are you?"},"5":{"name":"Lauren","message":"Is it time to do more, socially? "},"6":{"name":"Jason","message":"What about now?"},"7":{"name":"Jason","message":"Wake up"},"8":{"name":"Jason","message":"What happened"},"9":{"name":"Lauren","message":"What about over here?"},"10":{"name":"Jason","message":"Hello. My name Jason"}}